imagiz/__init__.py
imagiz-0.5.dist-info/METADATA
imagiz-0.5.dist-info/WHEEL
imagiz-0.5.dist-info/top_level.txt
imagiz-0.5.dist-info/RECORD
