Metadata-Version: 2.1
Name: imagiz
Version: 0.5
Summary: Live video streaming over network with OpenCV and (ZMQ or TCP)
Home-page: https://github.com/jmowlaei/imagiz
Author: Jafar Mowlaei
Author-email: jmowlaei@gmail.com
License: MIT
Platform: UNKNOWN
Requires-Dist: zmq
